TwitchChat/__init__.py
TwitchChat/twitch.py
TwitchChat-0.0.1.dist-info/LICENSE
TwitchChat-0.0.1.dist-info/METADATA
TwitchChat-0.0.1.dist-info/WHEEL
TwitchChat-0.0.1.dist-info/top_level.txt
TwitchChat-0.0.1.dist-info/RECORD
