Metadata-Version: 2.1
Name: TwitchChat
Version: 0.0.1
Summary: A basic wrapper for the twitch chat API
Home-page: https://github.com/SpitfireMk2b-san/TwitchChat
Author: SpitfireMk2b-san
License: UNKNOWN
Platform: UNKNOWN
Classifier: Programming Language :: Python :: 3
Classifier: License :: OSI Approved :: MIT License
Classifier: Operating System :: OS Independent
Requires-Python: >=3.6
